fast_api_fs/__init__.py
fast_api_fs/utils/Version.py
fast_api_fs/utils/__init__.py
fast_api_fs/version
fast_api_fs-0.1.3.dist-info/LICENSE
fast_api_fs-0.1.3.dist-info/METADATA
fast_api_fs-0.1.3.dist-info/WHEEL
fast_api_fs-0.1.3.dist-info/RECORD
