Metadata-Version: 2.3
Name: fast_api_fs
Version: 0.1.3
Summary: Fast-API-FS
License: Apache 2.0
Author: Dinis Cruz
Author-email: dinis.cruz@owasp.org
Requires-Python: >=3.12,<4.0
Classifier: License :: Other/Proprietary License
Classifier: Programming Language :: Python :: 3
Classifier: Programming Language :: Python :: 3.12
Classifier: Programming Language :: Python :: 3.13
Requires-Dist: osbot-utils
Project-URL: Homepage, https://github.com/owasp-sbot/Fast-API-FS
Project-URL: Repository, https://github.com/owasp-sbot/Fast-API-FS
